CHANGES.txt
README.md
setup.py
djinn_news/__init__.py
djinn_news/admin.py
djinn_news/search_indexes.py
djinn_news/settings.py
djinn_news/urls.py
djinn_news.egg-info/PKG-INFO
djinn_news.egg-info/SOURCES.txt
djinn_news.egg-info/dependency_links.txt
djinn_news.egg-info/entry_points.txt
djinn_news.egg-info/not-zip-safe
djinn_news.egg-info/requires.txt
djinn_news.egg-info/top_level.txt
djinn_news/forms/__init__.py
djinn_news/forms/news.py
djinn_news/forms/search.py
djinn_news/locale/en_EN/LC_MESSAGES/django.po
djinn_news/locale/nl_NL/LC_MESSAGES/django.po
djinn_news/management/__init__.py
djinn_news/migrations/0001_initial.py
djinn_news/migrations/0002_news_home_image.py
djinn_news/migrations/0003_news_is_sticky.py
djinn_news/migrations/__init__.py
djinn_news/models/__init__.py
djinn_news/models/news.py
djinn_news/models/signal_processors.py
djinn_news/static/js/djinn_news.js
djinn_news/templates/djinn_news/news_add.html
djinn_news/templates/djinn_news/news_detail.html
djinn_news/templates/djinn_news/news_edit.html
djinn_news/templates/djinn_news/news_overview_item.html
djinn_news/templates/djinn_news/snippets/news_viewlet.html
djinn_news/templates/indexes/news_index.txt
djinn_news/tests/__init__.py
djinn_news/tests/test_news.py
djinn_news/tests/test_newsviewlet.py
djinn_news/views/__init__.py
djinn_news/views/newsviewlet.py