Metadata-Version: 1.1
Name: djinn-news
Version: 1.1.6
Summary: Djinn Intranet News
Home-page: https://github.com/PythonUnited/djinn_news
Author: PythonUnited
Author-email: info@pythonunited.com
License: beer-ware
Keywords: Djinn Core
Platform: UNKNOWN
Classifier: Development Status :: 5 - Production/Stable
Classifier: Framework :: Django
Classifier: Intended Audience :: Developers
Classifier: License :: Freely Distributable
Classifier: Programming Language :: Python
Classifier: Topic :: Internet :: WWW/HTTP :: Site Management
Classifier: Topic :: Software Development :: Libraries :: Application Frameworks
